setup.cfg
setup.py
XsdLibrary/__init__.py
XsdLibrary/version.py
XsdLibrary/xsd.py
robotframework_xsd.egg-info/PKG-INFO
robotframework_xsd.egg-info/SOURCES.txt
robotframework_xsd.egg-info/dependency_links.txt
robotframework_xsd.egg-info/requires.txt
robotframework_xsd.egg-info/top_level.txt