Metadata-Version: 1.1
Name: robotframework-xsd
Version: 0.1.7
Summary: XSD validator for robotframework
Home-page: UNKNOWN
Author: mangobowl
Author-email: mangobowl@163.com
License: BSD License
Keywords: robotframework testing test automation xsd schema
Platform: any
Classifier: Development Status :: 5 - Production/Stable
Classifier: License :: OSI Approved :: BSD License
Classifier: Operating System :: OS Independent
Classifier: Programming Language :: Python
Classifier: Topic :: Software Development :: Testing
